BlochBuster/BlochBuster.py
BlochBuster/FFMPEGwriter.py
BlochBuster/__init__.py
blochbuster-1.2.0.dist-info/METADATA
blochbuster-1.2.0.dist-info/WHEEL
blochbuster-1.2.0.dist-info/licenses/LICENSE.md
blochbuster-1.2.0.dist-info/RECORD
