Metadata-Version: 2.4
Name: blochbuster
Version: 1.2.0
Summary: BlochBuster is a nuclear magnetic resonance Bloch equation simulator that creates animated plots.
Project-URL: Repository, https://github.com/bretglun/BlochBuster
Author-email: Johan Berglund <johan.berglund@akademiska.se>
License-Expression: GPL-3.0-or-later
License-File: LICENSE.md
Requires-Python: >=3.11
Requires-Dist: ffmpeg-python>=0.2.0
Requires-Dist: matplotlib>=3.10.5
Requires-Dist: pyyaml>=6.0.2
Requires-Dist: scipy>=1.16.1
Requires-Dist: static-ffmpeg>=2.13
